{
  "pip_freeze": {
    "absl-py": "2.1.0",
    "appdirs": "1.4.4",
    "astunparse": "1.6.3",
    "boto3": "1.36.10",
    "botocore": "1.36.10",
    "certifi": "2025.1.31",
    "charset-normalizer": "3.4.1",
    "colorama": "0.4.6",
    "dm-tree": "0.1.8",
    "dmiparser": "5.1",
    "filelock": "3.16.1",
    "fsspec": "2024.12.0",
    "gast": "0.6.0",
    "gitdb": "4.0.12",
    "GitPython": "3.1.44",
    "giturlparse": "0.12.0",
    "graphlib-backport": "1.1.0",
    "huggingface-hub": "0.28.1",
    "idna": "3.10",
    "importlib-resources": "6.4.5",
    "jmespath": "1.0.1",
    "Mako": "1.3.8",
    "MarkupSafe": "2.1.5",
    "mlcflow": "0.1.20",
    "mlcommons-loadgen": "5.0.13",
    "mlperf-logging": "4.1.3",
    "mpmath": "1.3.0",
    "nibabel": "5.2.1",
    "numpy": "1.23.5",
    "nvidia-dali-cuda120": "1.45.0",
    "nvidia-nvimgcodec-cu12": "0.3.0.5",
    "nvidia-pyindex": "1.0.9",
    "nvmitten": "0.1.3b0",
    "onnx": "1.13.1",
    "onnx-graphsurgeon": "0.3.27",
    "opencv-python": "4.11.0.86",
    "packaging": "24.2",
    "pandas": "1.5.3",
    "pip": "20.0.2",
    "platformdirs": "4.3.6",
    "protobuf": "3.20.3",
    "pybind11": "2.13.6",
    "pycuda": "2022.2.2",
    "python-dateutil": "2.9.0.post0",
    "pytools": "2024.1.14",
    "pytz": "2025.1",
    "PyYAML": "6.0.2",
    "regex": "2024.11.6",
    "requests": "2.32.3",
    "s3transfer": "0.11.2",
    "safetensors": "0.5.2",
    "scipy": "1.10.1",
    "setuptools": "45.2.0",
    "six": "1.16.0",
    "smmap": "5.0.2",
    "sympy": "1.13.3",
    "tabulate": "0.9.0",
    "tensorrt": "9.3.0.post12.dev1",
    "tensorrt-dispatch": "9.3.0.post12.dev1",
    "tensorrt-lean": "9.3.0.post12.dev1",
    "tokenizers": "0.20.3",
    "torch": "2.1.0a0+git32f93b1",
    "torchvision": "0.16.0a0+657027f",
    "tqdm": "4.67.1",
    "transformers": "4.46.3",
    "typing-extensions": "4.12.2",
    "tzdata": "2025.1",
    "urllib3": "2.2.3",
    "wheel": "0.34.2",
    "zipp": "3.20.2"
  }
}